pentageoserver/__init__.py
pentageoserver/src/Geoserver.py
pentageoserver/src/Postgres.py
pentageoserver/src/Style.py
pentageoserver/src/__init__.py
pentageoserver/src/pentageoserver.py
pentageoserver/src/supports.py
pentageoserver-1.2.0.dist-info/LICENSE
pentageoserver-1.2.0.dist-info/METADATA
pentageoserver-1.2.0.dist-info/WHEEL
pentageoserver-1.2.0.dist-info/top_level.txt
pentageoserver-1.2.0.dist-info/RECORD
