Metadata-Version: 2.1
Name: pentageoserver
Version: 1.2.0
Summary: Geoserver Automation Helper
Home-page: UNKNOWN
Author: ahmed mounir
License: UNKNOWN
Platform: UNKNOWN
Classifier: Programming Language :: Python :: 3
Classifier: License :: OSI Approved :: MIT License
Classifier: Operating System :: OS Independent
Requires-Python: >=3.6
License-File: LICENSE
Requires-Dist: seaborn
Requires-Dist: typing
Requires-Dist: matplotlib
Requires-Dist: temp
Requires-Dist: psycopg2-binary
Requires-Dist: requests
